activelink/__init__.py
activelink/templatetags/__init__.py
activelink/templatetags/activelink.py
activelink/tests/__init__.py
activelink/tests/tests.py
activelink/tests/urls.py
django_activelink-1.0.dist-info/DESCRIPTION.rst
django_activelink-1.0.dist-info/METADATA
django_activelink-1.0.dist-info/metadata.json
django_activelink-1.0.dist-info/RECORD
django_activelink-1.0.dist-info/top_level.txt
django_activelink-1.0.dist-info/WHEEL
