Metadata-Version: 2.0
Name: django-activelink
Version: 1.0
Summary: A Django template library for checking whether the current page matches a given URL. Useful for highlighting active links in menus.
Home-page: http://github.com/j4mie/django-activelink/
Author: Jamie Matthews
Author-email: jamie.matthews@gmail.com
License: UNKNOWN
Platform: UNKNOWN
Classifier: Programming Language :: Python
Classifier: Development Status :: 3 - Alpha
Classifier: Intended Audience :: Developers
Classifier: License :: Public Domain
Classifier: Framework :: Django
Classifier: Operating System :: OS Independent
